MANIFEST.in
email_template_view.xml
res_partner_demo.yml
res_partner_view.xml
setup.py
./__init__.py
./__openerp__.py
./email_template.py
./html2text.py
./res_partner.py
./tests/__init__.py
./tests/test_mail.py
./wizard/__init__.py
./wizard/email_template_preview.py
./wizard/mail_compose_message.py
i18n/ar.po
i18n/bg.po
i18n/bs.po
i18n/ca.po
i18n/cs.po
i18n/da.po
i18n/de.po
i18n/email_template.pot
i18n/en_GB.po
i18n/es.po
i18n/es_CL.po
i18n/es_CR.po
i18n/es_EC.po
i18n/es_MX.po
i18n/es_VE.po
i18n/et.po
i18n/fa_AF.po
i18n/fi.po
i18n/fr.po
i18n/he.po
i18n/hr.po
i18n/hu.po
i18n/it.po
i18n/ja.po
i18n/lt.po
i18n/mk.po
i18n/mn.po
i18n/nb.po
i18n/nl.po
i18n/nl_BE.po
i18n/pl.po
i18n/pt.po
i18n/pt_BR.po
i18n/ro.po
i18n/ru.po
i18n/sl.po
i18n/sr.po
i18n/sr@latin.po
i18n/sv.po
i18n/tr.po
i18n/zh_CN.po
i18n/zh_TW.po
images/1_email_account.jpeg
images/2_email_template.jpeg
images/3_emails.jpeg
openerp_email_template.egg-info/PKG-INFO
openerp_email_template.egg-info/SOURCES.txt
openerp_email_template.egg-info/dependency_links.txt
openerp_email_template.egg-info/requires.txt
openerp_email_template.egg-info/top_level.txt
security/ir.model.access.csv
static/src/img/email_template.png
static/src/img/email_template_save.png
wizard/email_template_preview_view.xml
wizard/mail_compose_message_view.xml